blackbox/__init__.py
blackbox/__main__.py
blackbox/cli.py
blackbox/config.py
blackbox/exceptions.py
blackbox/handlers/__init__.py
blackbox/handlers/_base.py
blackbox/handlers/databases/__init__.py
blackbox/handlers/databases/_base.py
blackbox/handlers/databases/localstorage.py
blackbox/handlers/databases/mariadb.py
blackbox/handlers/databases/mongodb.py
blackbox/handlers/databases/mysql.py
blackbox/handlers/databases/postgres.py
blackbox/handlers/databases/redis.py
blackbox/handlers/notifiers/__init__.py
blackbox/handlers/notifiers/_base.py
blackbox/handlers/notifiers/discord.py
blackbox/handlers/notifiers/json.py
blackbox/handlers/notifiers/slack.py
blackbox/handlers/notifiers/telegram.py
blackbox/handlers/storage/__init__.py
blackbox/handlers/storage/_base.py
blackbox/handlers/storage/dropbox.py
blackbox/handlers/storage/google_drive.py
blackbox/handlers/storage/s3.py
blackbox/utils/__init__.py
blackbox/utils/commands.py
blackbox/utils/cooldown.py
blackbox/utils/encryption.py
blackbox/utils/logger.py
blackbox/utils/mixins.py
blackbox/utils/reports.py
blackbox/utils/rotation.py
blackbox/utils/workflows.py
blackbox/utils/yaml.py
blackbox_cli-2.6.0.dist-info/entry_points.txt
blackbox_cli-2.6.0.dist-info/METADATA
blackbox_cli-2.6.0.dist-info/LICENSE
blackbox_cli-2.6.0.dist-info/WHEEL
blackbox_cli-2.6.0.dist-info/RECORD
