Metadata-Version: 2.1
Name: blackbox-cli
Version: 2.6.0
Summary: Tool for automatic backups of databases
Home-page: https://github.com/lemonsaurus/blackbox
License: MIT
Author: Leon Sandøy
Author-email: leon.sandoy@gmail.com
Requires-Python: >=3.9,<4.0
Classifier: Development Status :: 3 - Alpha
Classifier: License :: OSI Approved :: MIT License
Classifier: Operating System :: POSIX :: Linux
Classifier: Programming Language :: Python
Classifier: Programming Language :: Python :: 3
Classifier: Programming Language :: Python :: 3.9
Classifier: Programming Language :: Python :: 3.10
Classifier: Programming Language :: Python :: 3.11
Classifier: Programming Language :: Python :: 3.9
Classifier: Topic :: Database
Classifier: Topic :: System :: Archiving :: Backup
Requires-Dist: boto3 (>=1.16.51,<2.0.0)
Requires-Dist: click (>=7.1.2,<9.0.0)
Requires-Dist: cryptography (>=43.0.0,<44.0.0)
Requires-Dist: dropbox (>=11.0.0,<12.0.0)
Requires-Dist: google-api-python-client (>=2.160.0,<3.0.0)
Requires-Dist: jinja2 (>=3.1.6,<4.0.0)
Requires-Dist: loguru (>=0.5.3,<0.6.0)
Requires-Dist: pytelegrambotapi (>=4.27.0,<5.0.0)
Requires-Dist: pyyaml (>=6.0,<7.0)
Requires-Dist: requests (>=2.32.4,<3.0.0)
Requires-Dist: single-source (>=0.4.0,<0.5.0)
Requires-Dist: stone (>=3.2.1,<4.0.0)
Project-URL: Repository, https://github.com/lemonsaurus/blackbox
